animalsay/__init__.py
animalsay/__main__.py
animalsay/utils.py
animalsay/farm/__init__.py
animalsay/farm/animals.py
animalsay/home/__init__.py
animalsay/home/animals.py
animalsay-1.0.5.dist-info/LICENSE.txt
animalsay-1.0.5.dist-info/METADATA
animalsay-1.0.5.dist-info/WHEEL
animalsay-1.0.5.dist-info/top_level.txt
animalsay-1.0.5.dist-info/RECORD
