Metadata-Version: 2.1
Name: animalsay
Version: 1.0.5
Summary: A Python version of the famous cowsay program by Tony Monroe.
Home-page: https://github.com/gloriamacia/animalsay
Author: Gloria Macia
Author-email: gloria.macia@roche.com
License: MIT
Platform: UNKNOWN
Classifier: License :: OSI Approved :: MIT License
Classifier: Programming Language :: Python :: 3
Requires-Python: >=3.6
